gridlessEngine.py
gridlessEngine-0.0.2.dist-info/METADATA
gridlessEngine-0.0.2.dist-info/WHEEL
gridlessEngine-0.0.2.dist-info/top_level.txt
gridlessEngine-0.0.2.dist-info/RECORD
